{
  "$schema": "https://ui.shadcn.com/schema/registry-item.json",
  "name": "toggle",
  "type": "registry:component",
  "title": "Toggle",
  "description": "A two-state button that can be either on or off.",
  "dependencies": [
    "@radix-ui/react-toggle"
  ],
  "registryDependencies": [],
  "files": [
    {
      "path": "registry/ui/glass/toggle.tsx",
      "content": "\"use client\"\n\nimport * as React from \"react\"\nimport { Toggle as BaseToggle, toggleVariants } from \"@/registry/ui/toggle\"\nimport { cn } from \"@/lib/utils\"\n\nexport interface ToggleProps extends React.ComponentProps<typeof BaseToggle> {\n  glow?: boolean\n}\n\n/**\n * Glass UI Toggle - Enhanced toggle with glassy effects\n */\nexport const Toggle = React.forwardRef<\n  React.ElementRef<typeof BaseToggle>,\n  ToggleProps\n>(({ className, variant = \"glass\", glow = false, ...props }, ref) => {\n  return (\n    <BaseToggle\n      ref={ref}\n      variant={variant}\n      className={cn(\n        glow && \"data-[state=on]:shadow-lg data-[state=on]:shadow-purple-500/30\",\n        \"transition-all duration-200\",\n        className\n      )}\n      {...props}\n    />\n  )\n})\nToggle.displayName = \"Toggle\"\n\nexport { toggleVariants }\n\n",
      "type": "registry:component"
    }
  ]
}